qualesim_qcis/QCIS_inst.py
qualesim_qcis/QCIS_lexer.py
qualesim_qcis/QCIS_parser.py
qualesim_qcis/frontend.py
qualesim_qcis/utils.py
qualesim_qcis-1.0.1.data/data/bin/dqcsfeqcis
qualesim_qcis-1.0.1.dist-info/METADATA
qualesim_qcis-1.0.1.dist-info/WHEEL
qualesim_qcis-1.0.1.dist-info/top_level.txt
qualesim_qcis-1.0.1.dist-info/RECORD
