Metadata-Version: 2.1
Name: qualesim-qcis
Version: 1.0.1
Summary: QuaLeSim frontend for QCIS.
Home-page: https://gitee.com/hpcl_quanta/dqcsim-qcis.git
Author: Dingdong Liu
Author-email: dingdongliu@quanta.org.cn
License: GPLv3
Keywords: qualesim qcis
Classifier: Development Status :: 3 - Alpha
Classifier: Intended Audience :: Science/Research
Classifier: License :: OSI Approved :: GNU General Public License v3 (GPLv3)
Classifier: Topic :: Scientific/Engineering
Requires-Dist: numpy
Requires-Dist: ply
